nv_pylib_template/__init__.py
nv_pylib_template/__main__.py
nv_pylib_template/py.typed
nv_pylib_template/sample.py
nv_pylib_template-1.0.4.dist-info/METADATA
nv_pylib_template-1.0.4.dist-info/WHEEL
nv_pylib_template-1.0.4.dist-info/entry_points.txt
nv_pylib_template-1.0.4.dist-info/top_level.txt
nv_pylib_template-1.0.4.dist-info/RECORD
