Metadata-Version: 2.4
Name: nv-pylib-template
Version: 1.0.4
Summary: A Python library template with modern tooling and dual publishing support
Author-email: Your Name <your.email@example.com>
License: MIT
Classifier: Development Status :: 3 - Alpha
Classifier: Intended Audience :: Developers
Classifier: License :: OSI Approved :: MIT License
Classifier: Programming Language :: Python :: 3
Classifier: Programming Language :: Python :: 3.12
Classifier: Programming Language :: Python :: 3.13
Requires-Python: >=3.12
Provides-Extra: dev
Requires-Dist: ruff>=0.8.0; extra == "dev"
Requires-Dist: mypy>=1.13.0; extra == "dev"
Requires-Dist: pytest>=8.3.0; extra == "dev"
Requires-Dist: pytest-cov>=6.0.0; extra == "dev"
